django_full_kit/__init__.py
django_full_kit/admin.py
django_full_kit/apps.py
django_full_kit/models.py
django_full_kit/tests.py
django_full_kit/upload_paths.py
django_full_kit/urls.py
django_full_kit/views.py
django_full_kit/utils/validators.py
django_full_kit-0.2.0.dist-info/licenses/LICENSE
django_full_kit-0.2.0.dist-info/METADATA
django_full_kit-0.2.0.dist-info/WHEEL
django_full_kit-0.2.0.dist-info/top_level.txt
django_full_kit-0.2.0.dist-info/RECORD
