Metadata-Version: 2.4
Name: django-full-kit
Version: 0.2.0
Summary: A reusable Django package providing ready-to-use models, admin configurations, and utilities.
Author: aboalfazlH
License: MIT
Project-URL: Homepage, https://github.com/aboalfazlH/django-full-kit
Project-URL: Repository, https://github.com/aboalfazlH/django-full-kit
Project-URL: Issues, https://github.com/aboalfazlH/django-full-kit/issues
Keywords: django,django-package,django-reusable-app,backend,full-kit,django-full-kit
Classifier: Framework :: Django
Classifier: Framework :: Django :: 4.2
Classifier: Programming Language :: Python :: 3
Classifier: Programming Language :: Python :: 3 :: Only
Classifier: License :: OSI Approved :: MIT License
Classifier: Operating System :: OS Independent
Requires-Python: <3.13,>=3.10
License-File: LICENSE
Requires-Dist: Django<5.0,>=4.2
Requires-Dist: Pillow<11.0,>=10.0
Provides-Extra: dev
Requires-Dist: pytest>=7.0; extra == "dev"
Requires-Dist: pytest-django>=4.5; extra == "dev"
Dynamic: license-file
